i3dxrd-0.1.0b2-py3.7-nspkg.pth
i3dxrd/__init__.py
i3dxrd/data_selection.py
i3dxrd/dataset.py
i3dxrd/operationThread.py
i3dxrd/test_dataset.py
i3dxrd/utils.py
i3dxrd/version.py
i3dxrd/gui/__init__.py
i3dxrd/gui/backgroundSubtractionWidget.py
i3dxrd/gui/calibrationWidget.py
i3dxrd/gui/dataSelectionWidget.py
i3dxrd/gui/indexingWidget.py
i3dxrd/gui/makemapWidget.py
i3dxrd/gui/peakSearchWidget.py
i3dxrd/gui/plotMapWidget.py
i3dxrd/gui/showPeaksWidget.py
i3dxrd/gui/stackViewWidget.py
i3dxrd/test/__init__.py
i3dxrd/test/test_dataset.py
orangecontrib/i3dxrd/__init__.py
orangecontrib/i3dxrd/widgets/__init__.py
orangecontrib/i3dxrd/widgets/backgroundsubtraction.py
orangecontrib/i3dxrd/widgets/calibration.py
orangecontrib/i3dxrd/widgets/dataselection.py
orangecontrib/i3dxrd/widgets/indexing.py
orangecontrib/i3dxrd/widgets/makemap.py
orangecontrib/i3dxrd/widgets/peaksearch.py
orangecontrib/i3dxrd/widgets/plotmap.py
orangecontrib/i3dxrd/widgets/showpeaks.py
orangecontrib/i3dxrd/widgets/stackview.py
i3dxrd-0.1.0b2.dist-info/LICENSE
i3dxrd-0.1.0b2.dist-info/METADATA
i3dxrd-0.1.0b2.dist-info/WHEEL
i3dxrd-0.1.0b2.dist-info/entry_points.txt
i3dxrd-0.1.0b2.dist-info/namespace_packages.txt
i3dxrd-0.1.0b2.dist-info/top_level.txt
i3dxrd-0.1.0b2.dist-info/RECORD
