Metadata-Version: 2.1
Name: i3dxrd
Version: 0.1.0b2
Summary: Computer vision software for the interpretation of diffraction images
Home-page: https://gitlab.esrf.fr/XRD/i3dxrd
Author: data analysis unit
Author-email: julia.garriga@esrf.fr
License: MIT License
Platform: linux
Classifier: Development Status :: 3 - Alpha
Classifier: Environment :: Console
Classifier: Environment :: X11 Applications :: Qt
Classifier: Intended Audience :: Education
Classifier: Intended Audience :: Science/Research
Classifier: License :: OSI Approved :: MIT License
Classifier: Natural Language :: English
Classifier: Operating System :: POSIX
Classifier: Programming Language :: Python :: 3.4
Classifier: Programming Language :: Python :: 3.5
Classifier: Programming Language :: Python :: 3.6
Classifier: Programming Language :: Python :: 3.7
License-File: LICENSE
Requires-Dist: numpy
Requires-Dist: setuptools
Requires-Dist: darfix
Requires-Dist: silx
Requires-Dist: ImageD11
Provides-Extra: doc
Requires-Dist: sphinx ; extra == 'doc'
Requires-Dist: nbsphinx ; extra == 'doc'
Requires-Dist: recommonmark ; extra == 'doc'
Provides-Extra: full
Requires-Dist: matplotlib (>=1.2.0) ; extra == 'full'
Requires-Dist: opencv-python (==4.1.2.30) ; extra == 'full'
Requires-Dist: scikit-image (>=0.17.1) ; extra == 'full'
Requires-Dist: PyQt5 ; extra == 'full'
Requires-Dist: orange3 ; extra == 'full'
